krakenexapi/__init__.py
krakenexapi/api.py
krakenexapi-0.0.1.dist-info/AUTHORS.rst
krakenexapi-0.0.1.dist-info/LICENSE
krakenexapi-0.0.1.dist-info/METADATA
krakenexapi-0.0.1.dist-info/WHEEL
krakenexapi-0.0.1.dist-info/top_level.txt
krakenexapi-0.0.1.dist-info/RECORD
