Metadata-Version: 2.1
Name: krakenexapi
Version: 0.0.1
Summary: A Kraken Exchange API adapter.
Home-page: https://github.com/Querela/python-krakenexapi
Author: Erik Körner
Author-email: ekdev@live.de
License: MIT
Project-URL: Documentation, https://python-krakenexapi.readthedocs.io/
Project-URL: Changelog, https://python-krakenexapi.readthedocs.io/en/latest/changelog.html
Project-URL: Issue Tracker, https://github.com/Querela/python-krakenexapi/issues
Keywords: kraken,crypto,api
Platform: UNKNOWN
Classifier: Development Status :: 5 - Production/Stable
Classifier: Intended Audience :: Developers
Classifier: License :: OSI Approved :: MIT License
Classifier: Operating System :: Unix
Classifier: Operating System :: POSIX
Classifier: Operating System :: Microsoft :: Windows
Classifier: Programming Language :: Python
Classifier: Programming Language :: Python :: 3
Classifier: Programming Language :: Python :: 3 :: Only
Classifier: Programming Language :: Python :: 3.6
Classifier: Programming Language :: Python :: 3.7
Classifier: Programming Language :: Python :: 3.8
Classifier: Programming Language :: Python :: 3.9
Classifier: Programming Language :: Python :: 3.10
Classifier: Programming Language :: Python :: Implementation :: CPython
Classifier: Programming Language :: Python :: Implementation :: PyPy
Classifier: Topic :: Utilities
Requires-Python: >=3.6
Requires-Dist: requests (<3,>=2.25)
